jcevents/__init__.py
jcevents/event.py
jcevents/listener.py
jcevents/queue.py
jcevents-1.0.1.dist-info/METADATA
jcevents-1.0.1.dist-info/WHEEL
jcevents-1.0.1.dist-info/top_level.txt
jcevents-1.0.1.dist-info/RECORD
