Metadata-Version: 2.1
Name: jcevents
Version: 1.0.1
Summary: A lightweight event-driven framework for Python
Home-page: https://github.com/jencat42/jcevents
Author: Your Name
Author-email: gubenkovalik@gmail.com
License: MIT
Keywords: event-driven framework
Classifier: Development Status :: 5 - Production/Stable
Classifier: Intended Audience :: Developers
Classifier: License :: OSI Approved :: MIT License
Classifier: Programming Language :: Python :: 3
Classifier: Programming Language :: Python :: 3.6
Classifier: Programming Language :: Python :: 3.7
Classifier: Programming Language :: Python :: 3.8
Classifier: Programming Language :: Python :: 3.9
Classifier: Programming Language :: Python :: 3.10
Classifier: Topic :: Software Development :: Libraries
Classifier: Topic :: Software Development :: Libraries :: Python Modules
Requires-Python: >=3.6
